typerconf/.gitignore
typerconf/Makefile
typerconf/__init__.py
typerconf/init.nw
typerconf-2.10.dist-info/LICENSE
typerconf-2.10.dist-info/METADATA
typerconf-2.10.dist-info/WHEEL
typerconf-2.10.dist-info/RECORD
