Metadata-Version: 2.3
Name: typerconf
Version: 2.10
Summary: Library to read and write configs using API and CLI with Typer
License: MIT
Keywords: typer,conf,config,git-like,config lib,write conf
Author: Daniel Bosk
Author-email: daniel@bosk.se
Requires-Python: >=3.7,<4.0
Classifier: Environment :: Console
Classifier: License :: OSI Approved :: MIT License
Classifier: Operating System :: OS Independent
Classifier: Programming Language :: Python :: 3
Classifier: Programming Language :: Python :: 3.7
Classifier: Programming Language :: Python :: 3.8
Classifier: Programming Language :: Python :: 3.9
Classifier: Programming Language :: Python :: 3.10
Classifier: Programming Language :: Python :: 3.11
Classifier: Programming Language :: Python :: 3.12
Classifier: Programming Language :: Python :: 3.13
Classifier: Topic :: Utilities
Requires-Dist: appdirs (>=1.4.4,<2.0.0)
Requires-Dist: typer (>=0.9,<0.20)
Project-URL: Bug Tracker, https://github.com/dbosk/typerconf/issues
Project-URL: Repository, https://github.com/dbosk/typerconf
Project-URL: Releases, https://github.com/dbosk/typerconf/releases
